ploupy/__init__.py
ploupy/actions.py
ploupy/behaviour.py
ploupy/bot.py
ploupy/events.py
ploupy/gamemanager.py
ploupy/geometry.py
ploupy/order.py
ploupy/orders.py
ploupy/sio.py
ploupy/core/__init__.py
ploupy/core/config.py
ploupy/core/exceptions.py
ploupy/core/logger.py
ploupy/game/__init__.py
ploupy/game/entity.py
ploupy/game/factory.py
ploupy/game/game.py
ploupy/game/map.py
ploupy/game/player.py
ploupy/game/probe.py
ploupy/game/tile.py
ploupy/game/turret.py
ploupy/models/__init__.py
ploupy/models/api/__init__.py
ploupy/models/api/args.py
ploupy/models/api/responses.py
ploupy/models/core/__init__.py
ploupy/models/core/core.py
ploupy/models/game/__init__.py
ploupy/models/game/entities.py
ploupy/models/game/game.py
ploupy/models/sio/__init__.py
ploupy/models/sio/actions.py
ploupy/models/sio/responses.py
ploupy_sdk-0.2.1.dist-info/LICENSE.txt
ploupy_sdk-0.2.1.dist-info/METADATA
ploupy_sdk-0.2.1.dist-info/WHEEL
ploupy_sdk-0.2.1.dist-info/top_level.txt
ploupy_sdk-0.2.1.dist-info/RECORD
